akeyless_api_gateway/__init__.py
akeyless_api_gateway/api_client.py
akeyless_api_gateway/configuration.py
akeyless_api_gateway/rest.py
akeyless_api_gateway/api/__init__.py
akeyless_api_gateway/api/default_api.py
akeyless_api_gateway/models/__init__.py
akeyless_api_gateway/models/error_reply_obj.py
akeyless_api_gateway/models/reply_obj.py
test/__init__.py
test/test_default_api.py
test/test_error_reply_obj.py
test/test_reply_obj.py
akeyless_api_gateway-0.1.2.dist-info/METADATA
akeyless_api_gateway-0.1.2.dist-info/WHEEL
akeyless_api_gateway-0.1.2.dist-info/top_level.txt
akeyless_api_gateway-0.1.2.dist-info/RECORD
